bsv_integration/__init__.py
bsv_integration/admin.py
bsv_integration/apps.py
bsv_integration/models.py
bsv_integration/utils.py
bsv_integration/migrations/__init__.py
django_bsv_integration-0.1.0.dist-info/licenses/LICENSE
django_bsv_integration-0.1.0.dist-info/METADATA
django_bsv_integration-0.1.0.dist-info/WHEEL
django_bsv_integration-0.1.0.dist-info/top_level.txt
django_bsv_integration-0.1.0.dist-info/RECORD
